dnry/config/__init__.py
dnry/config/factory.py
dnry/config/helpers.py
dnry/config/section.py
dnry/config/types.py
dnry/config/arg/__init__.py
dnry/config/arg/source.py
dnry/config/delegate/__init__.py
dnry/config/delegate/source.py
dnry/config/environ/__init__.py
dnry/config/environ/source.py
dnry/config/in_memory/__init__.py
dnry/config/in_memory/source.py
dnry/config/yaml/__init__.py
dnry/config/yaml/source.py
dnry_config-0.1.4.dist-info/LICENSE
dnry_config-0.1.4.dist-info/METADATA
dnry_config-0.1.4.dist-info/WHEEL
dnry_config-0.1.4.dist-info/top_level.txt
dnry_config-0.1.4.dist-info/RECORD
