Metadata-Version: 2.1
Name: dnry-config
Version: 0.1.4
Summary: Multi-source config library
Home-page: https://github.com/en0/dnry-config
Author: Ian Laird
Author-email: irlaird@gmail.com
License: MIT
Keywords: config,configuration,dnry
Platform: UNKNOWN
Classifier: Programming Language :: Python :: 3
Classifier: License :: OSI Approved :: MIT License
Classifier: Operating System :: OS Independent
Requires-Dist: PyYAML
